fucker_110/__init__.py
fucker_110/hello.py
fucker_110-2.0.2.dist-info/WHEEL
fucker_110-2.0.2.dist-info/METADATA
fucker_110-2.0.2.dist-info/RECORD
