Metadata-Version: 2.1
Name: fucker-110
Version: 2.0.2
Summary: 
Author: 蒋经伟
Author-email: jingwei.jiang@mihoyo.com
Requires-Python: >=3.8,<4.0
Classifier: Programming Language :: Python :: 3
Classifier: Programming Language :: Python :: 3.8
Classifier: Programming Language :: Python :: 3.9
Requires-Dist: requests (>=2.28.0,<3.0.0)
